{
    "number_of_hotel": 1,
    "hotel": [
        {
            "hotel_id": "H0",
            "hotel_name": "1",
            "hotel_address": "1",
            "number_available_room": "2",
            "room": [
                {
                    "room_id": "H0_0S",
                    "room_type": "Single",
                    "room_price": 23453,
                    "room_availability": true,
                    "user_book": null,
                    "date_check_in": null,
                    "date_check_out": null,
                    "description": "Single",
                    "image_path": null
                },
                {
                    "room_id": "H0_12",
                    "room_type": "23456234",
                    "room_price": 2345,
                    "room_availability": true,
                    "user_book": null,
                    "date_check_in": null,
                    "date_check_out": null,
                    "description": "Beautiful",
                    "image_path": null
                }
            ]
        }
    ]
}